{
  "history": [
    {
      "epoch": 1,
      "train_loss": 2.308203517595927,
      "val_loss": 0.9402038252353668,
      "val_accuracy": 0.5855555555555556
    },
    {
      "epoch": 2,
      "train_loss": 0.5583408605555693,
      "val_loss": 0.4914045577579074,
      "val_accuracy": 0.5933333333333334
    },
    {
      "epoch": 3,
      "train_loss": 0.4858840326633718,
      "val_loss": 0.46672848009400897,
      "val_accuracy": 0.6233333333333333
    },
    {
      "epoch": 4,
      "train_loss": 0.4586690164109071,
      "val_loss": 0.44317503690719606,
      "val_accuracy": 0.6488888888888888
    },
    {
      "epoch": 5,
      "train_loss": 0.43018942489392226,
      "val_loss": 0.42588981199595666,
      "val_accuracy": 0.6633333333333333
    },
    {
      "epoch": 6,
      "train_loss": 0.4066456632564465,
      "val_loss": 0.41674914808736907,
      "val_accuracy": 0.6788888888888889
    },
    {
      "epoch": 7,
      "train_loss": 0.3843630397361186,
      "val_loss": 0.41601077215125165,
      "val_accuracy": 0.6844444444444444
    },
    {
      "epoch": 8,
      "train_loss": 0.36219441525845064,
      "val_loss": 0.42491638569782175,
      "val_accuracy": 0.6866666666666666
    },
    {
      "epoch": 9,
      "train_loss": 0.3411294073673586,
      "val_loss": 0.42027178643478286,
      "val_accuracy": 0.6866666666666666
    },
    {
      "epoch": 10,
      "train_loss": 0.32019063983216056,
      "val_loss": 0.42370561956117553,
      "val_accuracy": 0.6866666666666666
    },
    {
      "epoch": 11,
      "train_loss": 0.2990226317310913,
      "val_loss": 0.42983941406011583,
      "val_accuracy": 0.6933333333333334
    }
  ]
}